rsgiadapter-0.0.6.dist-info/METADATA
rsgiadapter-0.0.6.dist-info/WHEEL
rsgiadapter-0.0.6.dist-info/licenses/LICENSE
rsgiadapter/__init__.py
rsgiadapter/asgi.py
rsgiadapter/constant.py
rsgiadapter/lifespan.py
rsgiadapter/protocol.py
rsgiadapter/py.typed
rsgiadapter/response.py
rsgiadapter-0.0.6.dist-info/RECORD
