Metadata-Version: 2.1
Name: rsgiadapter
Version: 0.0.6
Summary: An adapter for asgi to rsgi
Keywords: asgi,rsgi,adapter,asgi adapter,rsgi adapter,asgi to rsgi,rsgi to asgi,asyncio
Author-Email: belingud <im.victor@qq.com>
License: BSD-3-Clause
Classifier: Programming Language :: Python :: 3
Classifier: Programming Language :: Python :: 3.8
Classifier: Programming Language :: Python :: 3.9
Classifier: Programming Language :: Python :: 3.10
Classifier: Programming Language :: Python :: 3.11
Classifier: Programming Language :: Python :: 3.12
Classifier: License :: OSI Approved :: BSD License
Classifier: Operating System :: OS Independent
Classifier: Development Status :: 3 - Alpha
Classifier: Intended Audience :: Developers
Classifier: Intended Audience :: Information Technology
Classifier: Intended Audience :: System Administrators
Classifier: Topic :: Internet
Classifier: Topic :: Internet :: WWW/HTTP
Classifier: Topic :: Internet :: WWW/HTTP :: HTTP Servers
Classifier: Topic :: Software Development :: Libraries :: Application Frameworks
Classifier: Topic :: Software Development :: Libraries :: Python Modules
Classifier: Topic :: Software Development :: Libraries
Classifier: Topic :: Software Development
Classifier: Typing :: Typed
Project-URL: Homepage, https://github.com/belingud/rsgiadapter
Requires-Python: <4.0,>=3.8
Provides-Extra: examples
Requires-Dist: setuptools>=70.0.0; extra == "examples"
Requires-Dist: fastapi>=0.111.0; extra == "examples"
Requires-Dist: granian>=1.4.1; extra == "examples"
Requires-Dist: sanic>=23.12.1; extra == "examples"
Requires-Dist: blacksheep>=2.0.7; extra == "examples"
Requires-Dist: litestar>=2.9.0; extra == "examples"
Requires-Dist: quart>=0.19.6; extra == "examples"
Requires-Dist: django>=4.2.13; extra == "examples"
Requires-Dist: falcon>=3.1.3; extra == "examples"
Requires-Dist: tornado>=6.4.1; extra == "examples"
